pyconstructor-0.2.2.dist-info/licenses/LICENSE
src/__init__.py
src/main.py
pyconstructor-0.2.2.dist-info/METADATA
pyconstructor-0.2.2.dist-info/WHEEL
pyconstructor-0.2.2.dist-info/entry_points.txt
pyconstructor-0.2.2.dist-info/top_level.txt
pyconstructor-0.2.2.dist-info/RECORD
