Metadata-Version: 2.4
Name: pyconstructor
Version: 0.2.2
Summary: CLI tool for generating DDD architecture in Python projects
Author-email: Grigoriy Sokolov <Sokolov_Gr@proton.me>
License: MIT License
Project-URL: Homepage, https://github.com/SokolovG/PyConstruct
Project-URL: Repository, https://github.com/SokolovG/PyConstruct
Project-URL: Issues, https://github.com/SokolovG/PyConstruct/issues
Keywords: ddd,architecture,code-generation,domain-driven-design
Classifier: Environment :: Console
Classifier: Intended Audience :: Developers
Classifier: License :: OSI Approved :: MIT License
Classifier: Programming Language :: Python :: 3.12
Classifier: Topic :: Software Development :: Code Generators
Requires-Python: >=3.12
License-File: LICENSE
Requires-Dist: click>=8.1.8
Requires-Dist: PyYAML>=6.0.2
Requires-Dist: pydantic>=2.11.3
Requires-Dist: dishka>=1.5.3
Requires-Dist: Jinja2>=3.1.6
Requires-Dist: rich>=14.0.0
Requires-Dist: pytest>=8.3.5
Provides-Extra: dev
Requires-Dist: pytest>=8.3.5; extra == "dev"
Requires-Dist: ruff>=0.11.6; extra == "dev"
Requires-Dist: mypy>=1.15.0; extra == "dev"
Requires-Dist: pre-commit>=4.2.0; extra == "dev"
Requires-Dist: pytest-cov>=6.1.1; extra == "dev"
Dynamic: license-file
